README.rst
setup.cfg
setup.py
minipay/__init__.py
minipay/base.py
minipay/config.py
minipay/exceptions.py
minipay/model.py
minipay.egg-info/PKG-INFO
minipay.egg-info/SOURCES.txt
minipay.egg-info/dependency_links.txt
minipay.egg-info/requires.txt
minipay.egg-info/top_level.txt