Metadata-Version: 1.1
Name: minipay
Version: 0.0.13
Summary: 微信小程序支付简易SDK
Home-page: https://github.com/dkodoc/minipay
Author: dkodoc
Author-email: tjm0510@163.com
License: MIT
Keywords: wechat,minipay,mini program,pay,sdk
Platform: any
Classifier: Environment :: Web Environment
Classifier: Intended Audience :: Developers
Classifier: Operating System :: OS Independent
Classifier: Topic :: Text Processing :: Indexing
Classifier: Topic :: Utilities
Classifier: Topic :: Internet
Classifier: Topic :: Software Development :: Libraries :: Python Modules
Classifier: Programming Language :: Python
Classifier: Programming Language :: Python :: 3.5
Classifier: Programming Language :: Python :: 3.6
Classifier: Programming Language :: Python :: 3.7
